deep_doors_2/__init__.py
deep_doors_2/__version__.py
deep_doors_2/door_sample.py
deep_doors_2_labelled/__init__.py
deep_doors_2_labelled/__version__.py
deep_doors_2_labelled-1.0.1.dist-info/LICENSE
deep_doors_2_labelled-1.0.1.dist-info/METADATA
deep_doors_2_labelled-1.0.1.dist-info/WHEEL
deep_doors_2_labelled-1.0.1.dist-info/entry_points.txt
deep_doors_2_labelled-1.0.1.dist-info/top_level.txt
deep_doors_2_labelled-1.0.1.dist-info/RECORD
