Metadata-Version: 2.1
Name: deep-doors-2-labelled
Version: 1.0.1
Summary: Deep doors 2 labelled dataset
Home-page: https://github.com/micheleantonazzi/deep-doors-2-labelled
Author: Michele Antonazzi
Author-email: micheleantonazzi@gmail.com
License: MIT
Platform: UNKNOWN
Classifier: License :: OSI Approved :: MIT License
Classifier: Programming Language :: Python :: 3
Requires-Dist: generic-dataset
Requires-Dist: numpy
Requires-Dist: opencv-python
Requires-Dist: stub-generator
Provides-Extra: test
Requires-Dist: pytest ; extra == 'test'
Requires-Dist: pytest-cov ; extra == 'test'
